functional/__init__.py
functional/foo.ini
korpokkur/__init__.py
korpokkur/command.py
korpokkur/compat.py
korpokkur/config.py
korpokkur/detector.py
korpokkur/input.py
korpokkur/interfaces.py
korpokkur/langhelper.py
korpokkur/reproduction.py
korpokkur/scaffoldgetter.py
korpokkur/testing.py
korpokkur/walker.py
korpokkur/emitter/__init__.py
korpokkur/emitter/jinja2.py
korpokkur/emitter/mako.py
korpokkur/emitter/transparent.py
korpokkur/scaffolds/__init__.py
korpokkur/scaffolds/__pycache__/__init__.cpython-33.pyc
korpokkur/scaffolds/nestedpackage/__init__.py
korpokkur/scaffolds/nestedpackage/+package+/CHANGES.txt
korpokkur/scaffolds/nestedpackage/+package+/README.rst.tmpl
korpokkur/scaffolds/nestedpackage/+package+/setup.py.tmpl
korpokkur/scaffolds/nestedpackage/+package+/+package_prefix+/__init__.py
korpokkur/scaffolds/nestedpackage/+package+/+package_prefix+/+package_suffix+/__init__.py
korpokkur/scaffolds/nestedpackage/+package+/+package_prefix+/+package_suffix+/tests/__init__.py
korpokkur/scaffolds/nestedpackage/__pycache__/__init__.cpython-33.pyc
korpokkur/scaffolds/nestedscaffold/__init__.py
korpokkur/scaffolds/nestedscaffold/+package+/Manifest.in.tmpl
korpokkur/scaffolds/nestedscaffold/+package+/setup.py.tmpl
korpokkur/scaffolds/nestedscaffold/+package+/+package_prefix+/__init__.py
korpokkur/scaffolds/nestedscaffold/+package+/+package_prefix+/+package_suffix+/__init__.py.tmpl
korpokkur/scaffolds/nestedscaffold/__pycache__/__init__.cpython-33.pyc
korpokkur/scaffolds/package/__init__.py
korpokkur/scaffolds/package/+package+/CHANGES.txt
korpokkur/scaffolds/package/+package+/README.rst.tmpl
korpokkur/scaffolds/package/+package+/setup.cfg
korpokkur/scaffolds/package/+package+/setup.py.tmpl
korpokkur/scaffolds/package/+package+/+module+/__init__.py
korpokkur/scaffolds/package/+package+/+module+/tests/__init__.py
korpokkur/scaffolds/package/__pycache__/__init__.cpython-33.pyc
korpokkur/scaffolds/pygitignore/__init__.py
korpokkur-0.1.dist-info/DESCRIPTION.rst
korpokkur-0.1.dist-info/entry_points.txt
korpokkur-0.1.dist-info/METADATA
korpokkur-0.1.dist-info/metadata.json
korpokkur-0.1.dist-info/RECORD
korpokkur-0.1.dist-info/top_level.txt
korpokkur-0.1.dist-info/WHEEL
